package_clara/__init__.py
package_clara/filel2_name.py
package_clara/filel_name.py
processing/__init__.py
processing/combination.py
processing/transformation.py
package_clara-0.0.2.dist-info/METADATA
package_clara-0.0.2.dist-info/WHEEL
package_clara-0.0.2.dist-info/top_level.txt
package_clara-0.0.2.dist-info/RECORD
