Metadata-Version: 2.4
Name: package_clara
Version: 0.0.2
Summary: Estou iniciando esse desafio com muito foco e atenção em relação ao desafio de processamento de imagens
Author: Anna_Clara
Author-email: claramoitinho67@gmail.com
Requires-Python: >=3.8
Dynamic: author
Dynamic: author-email
Dynamic: description
Dynamic: description-content-type
Dynamic: requires-python
Dynamic: summary
